odoo/addons/hr_payroll_cancel/README.rst
odoo/addons/hr_payroll_cancel/__init__.py
odoo/addons/hr_payroll_cancel/__manifest__.py
odoo/addons/hr_payroll_cancel/i18n/cs_CZ.po
odoo/addons/hr_payroll_cancel/i18n/de.po
odoo/addons/hr_payroll_cancel/i18n/es_AR.po
odoo/addons/hr_payroll_cancel/i18n/fr.po
odoo/addons/hr_payroll_cancel/i18n/hr_payroll_cancel.pot
odoo/addons/hr_payroll_cancel/i18n/sl.po
odoo/addons/hr_payroll_cancel/models/__init__.py
odoo/addons/hr_payroll_cancel/models/hr_payroll.py
odoo/addons/hr_payroll_cancel/readme/CONTRIBUTORS.rst
odoo/addons/hr_payroll_cancel/readme/DESCRIPTION.rst
odoo/addons/hr_payroll_cancel/readme/USAGE.rst
odoo/addons/hr_payroll_cancel/static/description/icon.png
odoo/addons/hr_payroll_cancel/static/description/index.html
odoo/addons/hr_payroll_cancel/tests/__init__.py
odoo/addons/hr_payroll_cancel/tests/test_hr_payroll_cancel.py
odoo/addons/hr_payroll_cancel/views/hr_payslip_view.xml
odoo14_addon_hr_payroll_cancel-14.0.1.1.0.dist-info/METADATA
odoo14_addon_hr_payroll_cancel-14.0.1.1.0.dist-info/WHEEL
odoo14_addon_hr_payroll_cancel-14.0.1.1.0.dist-info/top_level.txt
odoo14_addon_hr_payroll_cancel-14.0.1.1.0.dist-info/RECORD
